dcoderio/IO.py
dcoderio/__init__.py
dcoderio-0.4.dist-info/LICENSE.TXT
dcoderio-0.4.dist-info/METADATA
dcoderio-0.4.dist-info/WHEEL
dcoderio-0.4.dist-info/top_level.txt
dcoderio-0.4.dist-info/RECORD
