Metadata-Version: 2.1
Name: dcoderio
Version: 0.4
Summary: io lib for Dcoder
Home-page: https://github.com/dcodermobile/io-python
Author: dcodermobile
Author-email: support@dcoder.tech
License: MIT
Platform: UNKNOWN
